Metadata-Version: 2.1
Name: tcim
Version: 0.2.0
Summary: terminal commands in menus
Home-page: https://github.com/wups/tcim
Author: wups
License: GNU GPLv3
Platform: UNKNOWN
License-File: LICENSE
